gxredis/__init__.py
gxredis/dao.py
gxredis/decorator.py
gxredis/pubsub.py
gxredis/types.py
gxredis/util.py
gxredis-0.3.2.dist-info/LICENSE
gxredis-0.3.2.dist-info/METADATA
gxredis-0.3.2.dist-info/WHEEL
gxredis-0.3.2.dist-info/top_level.txt
gxredis-0.3.2.dist-info/RECORD
