Metadata-Version: 2.1
Name: gxredis
Version: 0.3.2
Summary: Simple redis-py wrapper library
Home-page: https://github.com/groove-x/gxredis
Author: Junya Hayashi
Author-email: junya.hayashi@groove-x.com
Maintainer: Junya Hayashi
Maintainer-email: junya-hayashi@groove-x.com
License: MIT
Keywords: Redis,key-value store
Platform: UNKNOWN
Classifier: Development Status :: 4 - Beta
Classifier: Intended Audience :: Developers
Classifier: License :: OSI Approved :: MIT License
Classifier: Operating System :: OS Independent
Classifier: Programming Language :: Python
Classifier: Programming Language :: Python :: 3
Classifier: Programming Language :: Python :: 3.3
Classifier: Programming Language :: Python :: 3.4
Classifier: Programming Language :: Python :: 3.5
Classifier: Programming Language :: Python :: 3.6
Classifier: Programming Language :: Python :: 3.7
Classifier: Topic :: Database
Requires-Dist: redis
